README.md
pyproject.toml
runner.py
docs/ATARI_ENVPOOL.md
docs/BRAX.md
docs/CONFIG_PARAMS.md
docs/ISAAC_GYM.md
docs/MUJOCO_ENVPOOL.md
docs/OTHER.md
docs/SMAC.md
docs/pictures/dqn_vs_dddqn.png
docs/pictures/mario_random_stages.png
docs/pictures/pong_dqn.png
docs/pictures/rainbow_dqn_breakout.jpg
docs/pictures/atari_envpool/breakout.jpg
docs/pictures/atari_envpool/breakout_envpool.png
docs/pictures/atari_envpool/pong.jpg
docs/pictures/atari_envpool/pong_envpool.png
docs/pictures/brax/brax_ant.jpg
docs/pictures/brax/brax_humanoid.jpg
docs/pictures/brax/brax_ur5e.jpg
docs/pictures/brax/humanoid.gif
docs/pictures/brax/ur5e.gif
docs/pictures/mujoco/half_cheetah.jpg
docs/pictures/mujoco/hopper.jpg
docs/pictures/mujoco/humanoid.jpg
docs/pictures/mujoco/mujoco_ant_envpool.png
docs/pictures/mujoco/mujoco_halfcheetah_envpool.png
docs/pictures/mujoco/mujoco_hopper_envpool.png
docs/pictures/mujoco/mujoco_humanoid_envpool.png
docs/pictures/mujoco/mujoco_walker2d_envpool.png
docs/pictures/mujoco/walker.jpg
docs/pictures/smac/2m_vs_1z.png
docs/pictures/smac/3s5z_vs_3s6z.png
docs/pictures/smac/3s_vs_5z.png
docs/pictures/smac/5m_vs_6m.png
docs/pictures/smac/MMM2.png
docs/pictures/smac/corridor.png
docs/pictures/smac/mmm2.gif
rl_games/__init__.py
rl_games/torch_runner.py
rl_games/__pycache__/__init__.cpython-37.pyc
rl_games/__pycache__/__init__.cpython-39.pyc
rl_games/__pycache__/torch_runner.cpython-37.pyc
rl_games/__pycache__/torch_runner.cpython-39.pyc
rl_games/algos_torch/__init__.py
rl_games/algos_torch/a2c_continuous.py
rl_games/algos_torch/a2c_discrete.py
rl_games/algos_torch/central_value.py
rl_games/algos_torch/d2rl.py
rl_games/algos_torch/flatten.py
rl_games/algos_torch/layers.py
rl_games/algos_torch/model_builder.py
rl_games/algos_torch/models.py
rl_games/algos_torch/moving_mean_std.py
rl_games/algos_torch/network_builder.py
rl_games/algos_torch/players.py
rl_games/algos_torch/running_mean_std.py
rl_games/algos_torch/sac_agent.py
rl_games/algos_torch/sac_helper.py
rl_games.egg-info/PKG-INFO
rl_games.egg-info/SOURCES.txt
rl_games.egg-info/dependency_links.txt
rl_games.egg-info/requires.txt
rl_games.egg-info/top_level.txt
rl_games-1.5.2.dist-info/LICENSE
rl_games-1.5.2.dist-info/METADATA
rl_games-1.5.2.dist-info/WHEEL
rl_games-1.5.2.dist-info/top_level.txt
rl_games-1.5.2.dist-info/RECORD
