Metadata-Version: 2.1
Name: rl-games
Version: 1.5.2
Summary: UNKNOWN
Home-page: https://github.com/Denys88/rl_games
Author: Denys Makoviichuk, Viktor Makoviichuk
Author-email: trrrrr97@gmail.com, victor.makoviychuk@gmail.com
License: MIT
Platform: UNKNOWN
Classifier: License :: OSI Approved :: MIT License
Classifier: Programming Language :: Python :: 3
Classifier: Programming Language :: Python :: 3.7
Classifier: Programming Language :: Python :: 3.8
Classifier: Programming Language :: Python :: 3.9
Requires-Dist: gym (>=0.17.2)
Requires-Dist: torch (>=1.7.0)
Requires-Dist: numpy (>=1.16.0)
Requires-Dist: ray (>=1.1.0)
Requires-Dist: tensorboard (>=1.14.0)
Requires-Dist: tensorboardX (>=1.6)
Requires-Dist: setproctitle
Requires-Dist: psutil
Requires-Dist: pyyaml
